codexium.py
codexium-0.2.0.dist-info/METADATA
codexium-0.2.0.dist-info/WHEEL
codexium-0.2.0.dist-info/entry_points.txt
codexium-0.2.0.dist-info/top_level.txt
codexium-0.2.0.dist-info/RECORD
