Metadata-Version: 2.4
Name: codexium
Version: 0.2.0
Summary: A CLI tool that automatically generates README files using AI
Home-page: https://github.com/bye-rez/codexium
Author: Alex Bairez
Classifier: Programming Language :: Python :: 3
Classifier: Operating System :: OS Independent
Classifier: Development Status :: 4 - Beta
Classifier: Intended Audience :: Developers
Classifier: Topic :: Software Development :: Documentation
Requires-Python: >=3.6
Requires-Dist: click>=8.0.0
Requires-Dist: cohere>=4.0.0
Dynamic: author
Dynamic: classifier
Dynamic: description
Dynamic: description-content-type
Dynamic: home-page
Dynamic: requires-dist
Dynamic: requires-python
Dynamic: summary
